graf/base.py
graf_orlock-0.0.0.dev0.dist-info/LICENSE
graf_orlock-0.0.0.dev0.dist-info/METADATA
graf_orlock-0.0.0.dev0.dist-info/WHEEL
graf_orlock-0.0.0.dev0.dist-info/top_level.txt
graf_orlock-0.0.0.dev0.dist-info/RECORD
