Metadata-Version: 2.1
Name: graf-orlock
Version: 0.0.0.dev0
Author-email: Grant Giesbrecht <grant.giesbrecht@colorado.edu>
Classifier: Programming Language :: Python :: 3
Classifier: License :: OSI Approved :: MIT License
Classifier: Operating System :: OS Independent
Requires-Python: >=3.8
License-File: LICENSE
Requires-Dist: h5py >=3.11.0
Requires-Dist: matplotlib >=3.9.1
